testdocs/__init__.py
testdocs/__main__.py
testdocs/exceptions.py
testdocs/module.py
testdocs/tests/__init__.py
testdocs/tests/test_testdoc.py
testdocs-0.1.2.dist-info/METADATA
testdocs-0.1.2.dist-info/WHEEL
testdocs-0.1.2.dist-info/entry_points.txt
testdocs-0.1.2.dist-info/RECORD
