Metadata-Version: 2.1
Name: testdocs
Version: 0.1.2
Summary: doctest++
Author: Evan Voyles
Author-email: evan.voyles@intrafentech.com
Requires-Python: >=3.11,<4.0
Classifier: Programming Language :: Python :: 3
Classifier: Programming Language :: Python :: 3.11
Classifier: Programming Language :: Python :: 3.12
